wheels2dmg/__init__.py
wheels2dmg/_version.py
wheels2dmg/piputils.py
wheels2dmg/pkgbuilders.py
wheels2dmg/tmpdirs.py
wheels2dmg/wheels2dmg_cmd.py
wheels2dmg/templates/Distribution
wheels2dmg/templates/first_install_python.webloc
wheels2dmg/templates/license.html
wheels2dmg/templates/postinstall
wheels2dmg/templates/README.txt
wheels2dmg/templates/requirements.txt
wheels2dmg/templates/welcome.html
wheels2dmg/tests/__init__.py
wheels2dmg/tests/scriptrunner.py
wheels2dmg/tests/test_piputils.py
wheels2dmg/tests/test_pkgbuilders.py
wheels2dmg/tests/test_wheels2dmg_cmd.py
wheels2dmg/tests/data/scipy-stack-1.0-plus.txt
wheels2dmg-0.1.data/scripts/wheels2dmg
wheels2dmg-0.1.dist-info/DESCRIPTION.rst
wheels2dmg-0.1.dist-info/METADATA
wheels2dmg-0.1.dist-info/metadata.json
wheels2dmg-0.1.dist-info/RECORD
wheels2dmg-0.1.dist-info/top_level.txt
wheels2dmg-0.1.dist-info/WHEEL
