Metadata-Version: 2.0
Name: wheels2dmg
Version: 0.1
Summary: Make pkg installer and dmg from wheels
Home-page: http://github.com/matthew-brett/wheels2dmg
Author: Matthew Brett
Author-email: matthew.brett@gmail.com
License: BSD license
Platform: UNKNOWN
Classifier: Intended Audience :: Developers
Classifier: Environment :: Console
Classifier: License :: OSI Approved :: BSD License
Classifier: Programming Language :: Python
Classifier: Operating System :: MacOS :: MacOS X
Classifier: Development Status :: 3 - Alpha
Classifier: Topic :: Software Development :: Libraries :: Python Modules
Classifier: Topic :: Software Development :: Build Tools
Requires-Dist: jinja2
Requires-Dist: wheel
Requires-Dist: delocate (>=0.6.0)
